bio/__init__.py
bio_python_25-0.1.0.dist-info/METADATA
bio_python_25-0.1.0.dist-info/WHEEL
bio_python_25-0.1.0.dist-info/top_level.txt
bio_python_25-0.1.0.dist-info/RECORD
