Metadata-Version: 2.1
Name: bio-python-25
Version: 0.1.0
Summary: Bioinformatics notebooks
Home-page: UNKNOWN
Author: asdf
Author-email: you@example.com
License: UNKNOWN
Platform: UNKNOWN
Classifier: Programming Language :: Python :: 3
Classifier: License :: OSI Approved :: MIT License
Classifier: Operating System :: OS Independent
Requires-Python: >=3.6
